{
  "sn56.11_001": {
    "text": "Ekaṁ samayaṁ bhagavā bārāṇasiyaṁ viharati isipatane migadāye.",
    "start": 1.8,
    "end": 5.38,
    "duration": 3.58,
    "words": [
      {
        "word": "Ekaṁ",
        "start": 1.8,
        "end": 2.3
      },
      {
        "word": "samayaṁ",
        "start": 2.3,
        "end": 4.66
      },
      {
        "word": "bhagavā",
        "start": 4.66,
        "end": 4.66
      },
      {
        "word": "bārāṇasiyaṁ",
        "start": 4.66,
        "end": 5.18
      },
      {
        "word": "viharati",
        "start": 5.18,
        "end": 5.18
      },
      {
        "word": "isipatane",
        "start": 5.18,
        "end": 5.38
      },
      {
        "word": "migadāye.",
        "start": 5.38,
        "end": 5.38
      }
    ]
  },
  "sn56.11_002": {
    "text": "Tatra kho bhagavā pañcavaggiye bhikkhū āmantesi:",
    "start": 5.38,
    "end": 5.84,
    "duration": 0.46,
    "words": [
      {
        "word": "Tatra",
        "start": 5.38,
        "end": 5.38
      },
      {
        "word": "kho",
        "start": 5.38,
        "end": 5.38
      },
      {
        "word": "bhagavā",
        "start": 5.38,
        "end": 5.38
      },
      {
        "word": "pañcavaggiye",
        "start": 5.38,
        "end": 5.84
      },
      {
        "word": "bhikkhū",
        "start": 5.84,
        "end": 5.84
      },
      {
        "word": "āmantesi:",
        "start": 5.84,
        "end": 5.84
      }
    ]
  },
  "sn56.11_003": {
    "text": "Dveme, bhikkhave, antā pabbajitena na sevitabbā.",
    "start": 5.84,
    "end": 7.97,
    "duration": 2.13,
    "words": [
      {
        "word": "Dveme,",
        "start": 5.84,
        "end": 5.84
      },
      {
        "word": "bhikkhave,",
        "start": 5.84,
        "end": 5.84
      },
      {
        "word": "antā",
        "start": 5.84,
        "end": 5.84
      },
      {
        "word": "pabbajitena",
        "start": 5.84,
        "end": 6.34
      },
      {
        "word": "na",
        "start": 6.34,
        "end": 6.72
      },
      {
        "word": "sevitabbā.",
        "start": 6.72,
        "end": 7.97
      }
    ]
  },
  "sn56.11_004": {
    "text": "Katame dve?",
    "start": 9.98,
    "end": 12.62,
    "duration": 2.64,
    "words": [
      {
        "word": "Katame",
        "start": 9.98,
        "end": 10.16
      },
      {
        "word": "dve?",
        "start": 11.26,
        "end": 12.62
      }
    ]
  },
  "sn56.11_005": {
    "text": "Yo cāyaṁ kāmesu kāmasukhallikānuyogo hīno gammo pothujjaniko anariyo anatthasaṁhito, yo cāyaṁ attakilamathānuyogo dukkho anariyo anatthasaṁhito.",
    "start": 12.88,
    "end": 24.64,
    "duration": 11.76,
    "words": [
      {
        "word": "Yo",
        "start": 12.88,
        "end": 13.44
      },
      {
        "word": "cāyaṁ",
        "start": 13.44,
        "end": 13.44
      },
      {
        "word": "kāmesu",
        "start": 13.98,
        "end": 15.5
      },
      {
        "word": "kāmasukhallikānuyogo",
        "start": 15.5,
        "end": 17.32
      },
      {
        "word": "hīno",
        "start": 17.32,
        "end": 17.32
      },
      {
        "word": "gammo",
        "start": 17.32,
        "end": 17.32
      },
      {
        "word": "pothujjaniko",
        "start": 17.32,
        "end": 17.32
      },
      {
        "word": "anariyo",
        "start": 17.32,
        "end": 17.32
      },
      {
        "word": "anatthasaṁhito,",
        "start": 17.32,
        "end": 17.32
      },
      {
        "word": "yo",
        "start": 17.66,
        "end": 17.76
      },
      {
        "word": "cāyaṁ",
        "start": 17.76,
        "end": 18.28
      },
      {
        "word": "attakilamathānuyogo",
        "start": 18.28,
        "end": 18.94
      },
      {
        "word": "dukkho",
        "start": 18.94,
        "end": 20.18
      },
      {
        "word": "anariyo",
        "start": 20.18,
        "end": 20.5
      },
      {
        "word": "anatthasaṁhito.",
        "start": 22.7,
        "end": 24.64
      }
    ]
  },
  "sn56.11_006": {
    "text": "Ete kho, bhikkhave, ubho ante anupagamma majjhimā paṭipadā tathāgatena abhisambuddhā cakkhukaraṇī ñāṇakaraṇī upasamāya abhiññāya sambodhāya nibbānāya saṁvattati.",
    "start": 25.7,
    "end": 54.3,
    "duration": 28.6,
    "words": [
      {
        "word": "Ete",
        "start": 25.7,
        "end": 25.8
      },
      {
        "word": "kho,",
        "start": 25.8,
        "end": 26.66
      },
      {
        "word": "bhikkhave,",
        "start": 27.72,
        "end": 27.86
      },
      {
        "word": "ubho",
        "start": 27.86,
        "end": 27.86
      },
      {
        "word": "ante",
        "start": 27.86,
        "end": 28.72
      },
      {
        "word": "anupagamma",
        "start": 28.72,
        "end": 31.32
      },
      {
        "word": "majjhimā",
        "start": 31.32,
        "end": 32.48
      },
      {
        "word": "paṭipadā",
        "start": 32.48,
        "end": 33.58
      },
      {
        "word": "tathāgatena",
        "start": 33.74,
        "end": 34.3
      },
      {
        "word": "abhisambuddhā",
        "start": 35.52,
        "end": 38.22
      },
      {
        "word": "cakkhukaraṇī",
        "start": 38.22,
        "end": 38.28
      },
      {
        "word": "ñāṇakaraṇī",
        "start": 38.28,
        "end": 40.18
      },
      {
        "word": "upasamāya",
        "start": 40.6,
        "end": 42.82
      },
      {
        "word": "abhiññāya",
        "start": 42.82,
        "end": 43.94
      },
      {
        "word": "sambodhāya",
        "start": 52.26,
        "end": 54.3
      },
      {
        "word": "nibbānāya",
        "start": 54.3,
        "end": 54.3
      },
      {
        "word": "saṁvattati.",
        "start": 54.3,
        "end": 54.3
      }
    ]
  },
  "sn56.11_007": {
    "text": "Katamā ca sā, bhikkhave, majjhimā paṭipadā tathāgatena abhisambuddhā cakkhukaraṇī ñāṇakaraṇī upasamāya abhiññāya sambodhāya nibbānāya saṁvattati?",
    "start": 54.3,
    "end": 78.92,
    "duration": 24.62,
    "words": [
      {
        "word": "Katamā",
        "start": 54.3,
        "end": 54.3
      },
      {
        "word": "ca",
        "start": 54.3,
        "end": 54.3
      },
      {
        "word": "sā,",
        "start": 54.3,
        "end": 55.32
      },
      {
        "word": "bhikkhave,",
        "start": 55.32,
        "end": 55.56
      },
      {
        "word": "majjhimā",
        "start": 55.56,
        "end": 55.56
      },
      {
        "word": "paṭipadā",
        "start": 55.56,
        "end": 55.86
      },
      {
        "word": "tathāgatena",
        "start": 55.86,
        "end": 56.24
      },
      {
        "word": "abhisambuddhā",
        "start": 56.24,
        "end": 58.26
      },
      {
        "word": "cakkhukaraṇī",
        "start": 58.26,
        "end": 59.21
      },
      {
        "word": "ñāṇakaraṇī",
        "start": 70.5,
        "end": 72.9
      },
      {
        "word": "upasamāya",
        "start": 72.9,
        "end": 73.52
      },
      {
        "word": "abhiññāya",
        "start": 73.52,
        "end": 74.5
      },
      {
        "word": "sambodhāya",
        "start": 74.5,
        "end": 75.98
      },
      {
        "word": "nibbānāya",
        "start": 75.98,
        "end": 76.54
      },
      {
        "word": "saṁvattati?",
        "start": 76.54,
        "end": 78.92
      }
    ]
  },
  "sn56.11_008": {
    "text": "Ayameva ariyo aṭṭhaṅgiko maggo, seyyathidaṁ—",
    "start": 82.28,
    "end": 88.66,
    "duration": 6.38,
    "words": [
      {
        "word": "Ayameva",
        "start": 82.28,
        "end": 82.68
      },
      {
        "word": "ariyo",
        "start": 82.68,
        "end": 82.84
      },
      {
        "word": "aṭṭhaṅgiko",
        "start": 82.84,
        "end": 83.0
      },
      {
        "word": "maggo,",
        "start": 87.3,
        "end": 88.66
      },
      {
        "word": "seyyathidaṁ—",
        "start": 88.66,
        "end": 88.66
      }
    ]
  },
  "sn56.11_009": {
    "text": "sammādiṭṭhi sammāsaṅkappo sammāvācā sammākammanto sammāājīvo sammāvāyāmo sammāsati sammāsamādhi.",
    "start": 95.78,
    "end": 125.84,
    "duration": 30.06,
    "words": [
      {
        "word": "sammādiṭṭhi",
        "start": 95.78,
        "end": 97.84
      },
      {
        "word": "sammāsaṅkappo",
        "start": 97.84,
        "end": 97.84
      },
      {
        "word": "sammāvācā",
        "start": 122.98,
        "end": 125.84
      },
      {
        "word": "sammākammanto",
        "start": 125.84,
        "end": 125.84
      },
      {
        "word": "sammāājīvo",
        "start": 125.84,
        "end": 125.84
      },
      {
        "word": "sammāvāyāmo",
        "start": 125.84,
        "end": 125.84
      },
      {
        "word": "sammāsati",
        "start": 125.84,
        "end": 125.84
      },
      {
        "word": "sammāsamādhi.",
        "start": 125.84,
        "end": 125.84
      }
    ]
  },
  "sn56.11_010": {
    "text": "Ayaṁ kho sā, bhikkhave, majjhimā paṭipadā tathāgatena abhisambuddhā cakkhukaraṇī ñāṇakaraṇī upasamāya abhiññāya sambodhāya nibbānāya saṁvattati.",
    "start": 125.84,
    "end": 149.02,
    "duration": 23.18,
    "words": [
      {
        "word": "Ayaṁ",
        "start": 125.84,
        "end": 125.84
      },
      {
        "word": "kho",
        "start": 125.84,
        "end": 125.84
      },
      {
        "word": "sā,",
        "start": 125.84,
        "end": 125.84
      },
      {
        "word": "bhikkhave,",
        "start": 125.84,
        "end": 126.12
      },
      {
        "word": "majjhimā",
        "start": 127.32,
        "end": 129.86
      },
      {
        "word": "paṭipadā",
        "start": 129.86,
        "end": 132.32
      },
      {
        "word": "tathāgatena",
        "start": 132.32,
        "end": 134.12
      },
      {
        "word": "abhisambuddhā",
        "start": 134.12,
        "end": 136.3
      },
      {
        "word": "cakkhukaraṇī",
        "start": 136.3,
        "end": 138.3
      },
      {
        "word": "ñāṇakaraṇī",
        "start": 138.3,
        "end": 140.32
      },
      {
        "word": "upasamāya",
        "start": 140.32,
        "end": 141.84
      },
      {
        "word": "abhiññāya",
        "start": 141.84,
        "end": 143.44
      },
      {
        "word": "sambodhāya",
        "start": 143.44,
        "end": 145.38
      },
      {
        "word": "nibbānāya",
        "start": 145.38,
        "end": 147.24
      },
      {
        "word": "saṁvattati.",
        "start": 147.24,
        "end": 149.02
      }
    ]
  },
  "sn56.11_011": {
    "text": "Idaṁ kho pana, bhikkhave, dukkhaṁ ariyasaccaṁ—",
    "start": 149.24,
    "end": 153.44,
    "duration": 4.2,
    "words": [
      {
        "word": "Idaṁ",
        "start": 149.24,
        "end": 149.5
      },
      {
        "word": "kho",
        "start": 149.5,
        "end": 149.78
      },
      {
        "word": "pana,",
        "start": 149.78,
        "end": 150.48
      },
      {
        "word": "bhikkhave,",
        "start": 150.76,
        "end": 152.12
      },
      {
        "word": "dukkhaṁ",
        "start": 152.18,
        "end": 152.4
      },
      {
        "word": "ariyasaccaṁ—",
        "start": 152.4,
        "end": 153.44
      }
    ]
  },
  "sn56.11_012": {
    "text": "jātipi dukkhā, jarāpi dukkhā, byādhipi dukkho, maraṇampi dukkhaṁ, appiyehi sampayogo dukkho, piyehi vippayogo dukkho, yampicchaṁ na labhati tampi dukkhaṁ—saṅkhittena pañcupādānakkhandhā dukkhā.",
    "start": 153.44,
    "end": 205.7,
    "duration": 52.26,
    "words": [
      {
        "word": "jātipi",
        "start": 153.44,
        "end": 153.58
      },
      {
        "word": "dukkhā,",
        "start": 153.58,
        "end": 154.64
      },
      {
        "word": "jarāpi",
        "start": 155.74,
        "end": 156.74
      },
      {
        "word": "dukkhā,",
        "start": 156.74,
        "end": 157.9
      },
      {
        "word": "byādhipi",
        "start": 160.1,
        "end": 160.62
      },
      {
        "word": "dukkho,",
        "start": 160.62,
        "end": 160.62
      },
      {
        "word": "maraṇampi",
        "start": 160.62,
        "end": 160.62
      },
      {
        "word": "dukkhaṁ,",
        "start": 160.62,
        "end": 160.62
      },
      {
        "word": "appiyehi",
        "start": 160.62,
        "end": 163.06
      },
      {
        "word": "sampayogo",
        "start": 163.06,
        "end": 165.3
      },
      {
        "word": "dukkho,",
        "start": 165.3,
        "end": 167.32
      },
      {
        "word": "piyehi",
        "start": 167.32,
        "end": 167.32
      },
      {
        "word": "vippayogo",
        "start": 167.32,
        "end": 169.26
      },
      {
        "word": "dukkho,",
        "start": 169.26,
        "end": 169.8
      },
      {
        "word": "yampicchaṁ",
        "start": 170.46,
        "end": 170.46
      },
      {
        "word": "na",
        "start": 170.46,
        "end": 170.46
      },
      {
        "word": "labhati",
        "start": 170.46,
        "end": 170.52
      },
      {
        "word": "tampi",
        "start": 176.9,
        "end": 179.06
      },
      {
        "word": "dukkhaṁ—saṅkhittena",
        "start": 198.22,
        "end": 201.0
      },
      {
        "word": "pañcupādānakkhandhā",
        "start": 201.0,
        "end": 203.16
      },
      {
        "word": "dukkhā.",
        "start": 205.28,
        "end": 205.7
      }
    ]
  },
  "sn56.11_013": {
    "text": "Idaṁ kho pana, bhikkhave, dukkhasamudayaṁ ariyasaccaṁ—",
    "start": 207.64,
    "end": 224.02,
    "duration": 16.38,
    "words": [
      {
        "word": "Idaṁ",
        "start": 207.64,
        "end": 210.6
      },
      {
        "word": "kho",
        "start": 210.6,
        "end": 210.6
      },
      {
        "word": "pana,",
        "start": 216.38,
        "end": 217.38
      },
      {
        "word": "bhikkhave,",
        "start": 220.24,
        "end": 221.16
      },
      {
        "word": "dukkhasamudayaṁ",
        "start": 221.42,
        "end": 222.64
      },
      {
        "word": "ariyasaccaṁ—",
        "start": 222.64,
        "end": 224.02
      }
    ]
  },
  "sn56.11_014": {
    "text": "yāyaṁ taṇhā ponobbhavikā nandirāgasahagatā tatratatrābhinandinī, seyyathidaṁ—",
    "start": 224.02,
    "end": 227.7,
    "duration": 3.68,
    "words": [
      {
        "word": "yāyaṁ",
        "start": 224.02,
        "end": 225.1
      },
      {
        "word": "taṇhā",
        "start": 225.1,
        "end": 226.3
      },
      {
        "word": "ponobbhavikā",
        "start": 226.3,
        "end": 226.3
      },
      {
        "word": "nandirāgasahagatā",
        "start": 226.3,
        "end": 226.3
      },
      {
        "word": "tatratatrābhinandinī,",
        "start": 226.3,
        "end": 227.38
      },
      {
        "word": "seyyathidaṁ—",
        "start": 227.38,
        "end": 227.7
      }
    ]
  },
  "sn56.11_015": {
    "text": "kāmataṇhā, bhavataṇhā, vibhavataṇhā.",
    "start": 255.2,
    "end": 256.5,
    "duration": 1.3,
    "words": [
      {
        "word": "kāmataṇhā,",
        "start": 255.2,
        "end": 256.5
      },
      {
        "word": "bhavataṇhā,",
        "start": 256.5,
        "end": 256.5
      },
      {
        "word": "vibhavataṇhā.",
        "start": 256.5,
        "end": 256.5
      }
    ]
  },
  "sn56.11_016": {
    "text": "Idaṁ kho pana, bhikkhave, dukkhanirodhaṁ ariyasaccaṁ—",
    "start": 256.5,
    "end": 263.22,
    "duration": 6.72,
    "words": [
      {
        "word": "Idaṁ",
        "start": 256.5,
        "end": 257.12
      },
      {
        "word": "kho",
        "start": 257.12,
        "end": 257.38
      },
      {
        "word": "pana,",
        "start": 257.38,
        "end": 258.16
      },
      {
        "word": "bhikkhave,",
        "start": 258.3,
        "end": 259.4
      },
      {
        "word": "dukkhanirodhaṁ",
        "start": 259.44,
        "end": 260.98
      },
      {
        "word": "ariyasaccaṁ—",
        "start": 260.98,
        "end": 263.22
      }
    ]
  },
  "sn56.11_017": {
    "text": "yo tassāyeva taṇhāya asesavirāganirodho cāgo paṭinissaggo mutti anālayo.",
    "start": 263.22,
    "end": 299.78,
    "duration": 36.56,
    "words": [
      {
        "word": "yo",
        "start": 263.22,
        "end": 263.38
      },
      {
        "word": "tassāyeva",
        "start": 263.38,
        "end": 264.32
      },
      {
        "word": "taṇhāya",
        "start": 290.76,
        "end": 291.22
      },
      {
        "word": "asesavirāganirodho",
        "start": 291.22,
        "end": 294.08
      },
      {
        "word": "cāgo",
        "start": 294.08,
        "end": 294.98
      },
      {
        "word": "paṭinissaggo",
        "start": 294.98,
        "end": 297.3
      },
      {
        "word": "mutti",
        "start": 297.3,
        "end": 298.04
      },
      {
        "word": "anālayo.",
        "start": 298.04,
        "end": 299.78
      }
    ]
  },
  "sn56.11_018": {
    "text": "Idaṁ kho pana, bhikkhave, dukkhanirodhagāminī paṭipadā ariyasaccaṁ—",
    "start": 299.88,
    "end": 308.96,
    "duration": 9.08,
    "words": [
      {
        "word": "Idaṁ",
        "start": 299.88,
        "end": 300.38
      },
      {
        "word": "kho",
        "start": 300.38,
        "end": 300.72
      },
      {
        "word": "pana,",
        "start": 300.72,
        "end": 301.5
      },
      {
        "word": "bhikkhave,",
        "start": 301.62,
        "end": 302.78
      },
      {
        "word": "dukkhanirodhagāminī",
        "start": 302.78,
        "end": 305.64
      },
      {
        "word": "paṭipadā",
        "start": 305.64,
        "end": 306.92
      },
      {
        "word": "ariyasaccaṁ—",
        "start": 306.92,
        "end": 308.96
      }
    ]
  },
  "sn56.11_019": {
    "text": "ayameva ariyo aṭṭhaṅgiko maggo, seyyathidaṁ—",
    "start": 308.96,
    "end": 316.88,
    "duration": 7.92,
    "words": [
      {
        "word": "ayameva",
        "start": 308.96,
        "end": 310.06
      },
      {
        "word": "ariyo",
        "start": 310.06,
        "end": 311.04
      },
      {
        "word": "aṭṭhaṅgiko",
        "start": 311.04,
        "end": 312.7
      },
      {
        "word": "maggo,",
        "start": 312.7,
        "end": 314.04
      },
      {
        "word": "seyyathidaṁ—",
        "start": 314.04,
        "end": 316.88
      }
    ]
  },
  "sn56.11_020": {
    "text": "sammādiṭṭhi sammāsaṅkappo sammāvācā sammākammanto sammāājīvo sammāvāyāmo sammāsati sammāsamādhi.",
    "start": 316.88,
    "end": 335.08,
    "duration": 18.2,
    "words": [
      {
        "word": "sammādiṭṭhi",
        "start": 316.88,
        "end": 317.54
      },
      {
        "word": "sammāsaṅkappo",
        "start": 317.54,
        "end": 319.92
      },
      {
        "word": "sammāvācā",
        "start": 319.92,
        "end": 322.02
      },
      {
        "word": "sammākammanto",
        "start": 322.02,
        "end": 324.36
      },
      {
        "word": "sammāājīvo",
        "start": 324.36,
        "end": 327.06
      },
      {
        "word": "sammāvāyāmo",
        "start": 327.06,
        "end": 329.72
      },
      {
        "word": "sammāsati",
        "start": 329.72,
        "end": 331.42
      },
      {
        "word": "sammāsamādhi.",
        "start": 332.96,
        "end": 335.08
      }
    ]
  },
  "sn56.11_021": {
    "text": "Idaṁ dukkhaṁ ariyasaccan'ti me, bhikkhave, pubbe ananussutesu dhammesu cakkhuṁ udapādi, ñāṇaṁ udapādi, paññā udapādi, vijjā udapādi, āloko udapādi.",
    "start": 335.44,
    "end": 355.4,
    "duration": 19.96,
    "words": [
      {
        "word": "Idaṁ",
        "start": 335.44,
        "end": 335.74
      },
      {
        "word": "dukkhaṁ",
        "start": 335.74,
        "end": 336.72
      },
      {
        "word": "ariyasaccan'ti",
        "start": 336.72,
        "end": 338.78
      },
      {
        "word": "me,",
        "start": 338.78,
        "end": 339.42
      },
      {
        "word": "bhikkhave,",
        "start": 339.72,
        "end": 340.76
      },
      {
        "word": "pubbe",
        "start": 340.9,
        "end": 341.46
      },
      {
        "word": "ananussutesu",
        "start": 341.46,
        "end": 343.66
      },
      {
        "word": "dhammesu",
        "start": 343.66,
        "end": 344.92
      },
      {
        "word": "cakkhuṁ",
        "start": 344.92,
        "end": 346.08
      },
      {
        "word": "udapādi,",
        "start": 346.08,
        "end": 347.2
      },
      {
        "word": "ñāṇaṁ",
        "start": 347.34,
        "end": 348.36
      },
      {
        "word": "udapādi,",
        "start": 348.36,
        "end": 349.58
      },
      {
        "word": "paññā",
        "start": 349.84,
        "end": 350.42
      },
      {
        "word": "udapādi,",
        "start": 350.42,
        "end": 352.08
      },
      {
        "word": "vijjā",
        "start": 352.14,
        "end": 352.8
      },
      {
        "word": "udapādi,",
        "start": 352.8,
        "end": 354.46
      },
      {
        "word": "āloko",
        "start": 354.68,
        "end": 355.3
      },
      {
        "word": "udapādi.",
        "start": 355.3,
        "end": 355.4
      }
    ]
  },
  "sn56.11_022": {
    "text": "Taṁ kho panidaṁ dukkhaṁ ariyasaccaṁ pariññeyyan'ti me, bhikkhave, pubbe ananussutesu dhammesu cakkhuṁ udapādi, ñāṇaṁ udapādi, paññā udapādi, vijjā udapādi, āloko udapādi.",
    "start": 357.4,
    "end": 382.1,
    "duration": 24.7,
    "words": [
      {
        "word": "Taṁ",
        "start": 357.4,
        "end": 357.52
      },
      {
        "word": "kho",
        "start": 357.52,
        "end": 357.8
      },
      {
        "word": "panidaṁ",
        "start": 357.8,
        "end": 359.06
      },
      {
        "word": "dukkhaṁ",
        "start": 359.06,
        "end": 360.08
      },
      {
        "word": "ariyasaccaṁ",
        "start": 360.08,
        "end": 361.92
      },
      {
        "word": "pariññeyyan'ti",
        "start": 361.92,
        "end": 363.78
      },
      {
        "word": "me,",
        "start": 363.78,
        "end": 364.4
      },
      {
        "word": "bhikkhave,",
        "start": 364.7,
        "end": 365.74
      },
      {
        "word": "pubbe",
        "start": 365.96,
        "end": 366.42
      },
      {
        "word": "ananussutesu",
        "start": 366.42,
        "end": 368.62
      },
      {
        "word": "dhammesu",
        "start": 368.62,
        "end": 369.86
      },
      {
        "word": "cakkhuṁ",
        "start": 369.86,
        "end": 370.98
      },
      {
        "word": "udapādi,",
        "start": 370.98,
        "end": 372.18
      },
      {
        "word": "ñāṇaṁ",
        "start": 372.42,
        "end": 373.36
      },
      {
        "word": "udapādi,",
        "start": 373.36,
        "end": 374.6
      },
      {
        "word": "paññā",
        "start": 374.74,
        "end": 375.36
      },
      {
        "word": "udapādi,",
        "start": 375.36,
        "end": 377.02
      },
      {
        "word": "vijjā",
        "start": 377.02,
        "end": 377.76
      },
      {
        "word": "udapādi,",
        "start": 377.76,
        "end": 379.34
      },
      {
        "word": "āloko",
        "start": 379.6,
        "end": 380.24
      },
      {
        "word": "udapādi.",
        "start": 380.24,
        "end": 382.1
      }
    ]
  },
  "sn56.11_023": {
    "text": "Taṁ kho panidaṁ dukkhaṁ ariyasaccaṁ pariññātan'ti me, bhikkhave, pubbe ananussutesu dhammesu cakkhuṁ udapādi, ñāṇaṁ udapādi, paññā udapādi, vijjā udapādi, āloko udapādi.",
    "start": 382.48,
    "end": 407.5,
    "duration": 25.02,
    "words": [
      {
        "word": "Taṁ",
        "start": 382.48,
        "end": 382.48
      },
      {
        "word": "kho",
        "start": 382.48,
        "end": 382.76
      },
      {
        "word": "panidaṁ",
        "start": 382.76,
        "end": 384.08
      },
      {
        "word": "dukkhaṁ",
        "start": 384.08,
        "end": 385.04
      },
      {
        "word": "ariyasaccaṁ",
        "start": 385.04,
        "end": 386.8
      },
      {
        "word": "pariññātan'ti",
        "start": 386.8,
        "end": 388.72
      },
      {
        "word": "me,",
        "start": 388.72,
        "end": 389.34
      },
      {
        "word": "bhikkhave,",
        "start": 389.64,
        "end": 390.68
      },
      {
        "word": "pubbe",
        "start": 390.88,
        "end": 391.36
      },
      {
        "word": "ananussutesu",
        "start": 391.36,
        "end": 393.58
      },
      {
        "word": "dhammesu",
        "start": 393.58,
        "end": 394.84
      },
      {
        "word": "cakkhuṁ",
        "start": 394.84,
        "end": 395.96
      },
      {
        "word": "udapādi,",
        "start": 395.96,
        "end": 397.34
      },
      {
        "word": "ñāṇaṁ",
        "start": 397.36,
        "end": 398.32
      },
      {
        "word": "udapādi,",
        "start": 398.32,
        "end": 399.64
      },
      {
        "word": "paññā",
        "start": 399.78,
        "end": 400.32
      },
      {
        "word": "udapādi,",
        "start": 400.32,
        "end": 402.04
      },
      {
        "word": "vijjā",
        "start": 402.2,
        "end": 402.76
      },
      {
        "word": "udapādi,",
        "start": 402.76,
        "end": 404.42
      },
      {
        "word": "āloko",
        "start": 404.58,
        "end": 405.28
      },
      {
        "word": "udapādi.",
        "start": 405.28,
        "end": 407.5
      }
    ]
  },
  "sn56.11_024": {
    "text": "Idaṁ dukkhasamudayaṁ ariyasaccan'ti me, bhikkhave, pubbe ananussutesu dhammesu cakkhuṁ udapādi, ñāṇaṁ udapādi, paññā udapādi, vijjā udapādi, āloko udapādi.",
    "start": 407.6,
    "end": 430.42,
    "duration": 22.82,
    "words": [
      {
        "word": "Idaṁ",
        "start": 407.6,
        "end": 407.88
      },
      {
        "word": "dukkhasamudayaṁ",
        "start": 407.88,
        "end": 409.62
      },
      {
        "word": "ariyasaccan'ti",
        "start": 409.62,
        "end": 411.82
      },
      {
        "word": "me,",
        "start": 411.82,
        "end": 412.44
      },
      {
        "word": "bhikkhave,",
        "start": 412.7,
        "end": 413.74
      },
      {
        "word": "pubbe",
        "start": 413.92,
        "end": 414.46
      },
      {
        "word": "ananussutesu",
        "start": 414.46,
        "end": 416.68
      },
      {
        "word": "dhammesu",
        "start": 416.68,
        "end": 417.92
      },
      {
        "word": "cakkhuṁ",
        "start": 417.92,
        "end": 419.02
      },
      {
        "word": "udapādi,",
        "start": 419.02,
        "end": 420.42
      },
      {
        "word": "ñāṇaṁ",
        "start": 420.42,
        "end": 421.5
      },
      {
        "word": "udapādi,",
        "start": 421.5,
        "end": 422.78
      },
      {
        "word": "paññā",
        "start": 422.88,
        "end": 423.56
      },
      {
        "word": "udapādi,",
        "start": 423.56,
        "end": 425.16
      },
      {
        "word": "vijjā",
        "start": 425.26,
        "end": 425.86
      },
      {
        "word": "udapādi,",
        "start": 425.86,
        "end": 427.54
      },
      {
        "word": "āloko",
        "start": 427.76,
        "end": 428.42
      },
      {
        "word": "udapādi.",
        "start": 428.42,
        "end": 430.42
      }
    ]
  },
  "sn56.11_025": {
    "text": "Taṁ kho panidaṁ dukkhasamudayaṁ ariyasaccaṁ pahātabban'ti me, bhikkhave, pubbe ananussutesu dhammesu cakkhuṁ udapādi, ñāṇaṁ udapādi, paññā udapādi, vijjā udapādi, āloko udapādi.",
    "start": 430.42,
    "end": 457.58,
    "duration": 27.16,
    "words": [
      {
        "word": "Taṁ",
        "start": 430.42,
        "end": 430.72
      },
      {
        "word": "kho",
        "start": 430.72,
        "end": 431.34
      },
      {
        "word": "panidaṁ",
        "start": 431.34,
        "end": 432.26
      },
      {
        "word": "dukkhasamudayaṁ",
        "start": 432.26,
        "end": 434.1
      },
      {
        "word": "ariyasaccaṁ",
        "start": 434.1,
        "end": 435.96
      },
      {
        "word": "pahātabban'ti",
        "start": 435.96,
        "end": 437.94
      },
      {
        "word": "me,",
        "start": 437.94,
        "end": 438.54
      },
      {
        "word": "bhikkhave,",
        "start": 438.82,
        "end": 439.84
      },
      {
        "word": "pubbe",
        "start": 440.12,
        "end": 440.52
      },
      {
        "word": "ananussutesu",
        "start": 440.52,
        "end": 442.76
      },
      {
        "word": "dhammesu",
        "start": 442.76,
        "end": 444.02
      },
      {
        "word": "cakkhuṁ",
        "start": 444.02,
        "end": 445.14
      },
      {
        "word": "udapādi,",
        "start": 445.14,
        "end": 446.3
      },
      {
        "word": "ñāṇaṁ",
        "start": 446.52,
        "end": 447.52
      },
      {
        "word": "udapādi,",
        "start": 447.52,
        "end": 448.82
      },
      {
        "word": "paññā",
        "start": 448.98,
        "end": 449.56
      },
      {
        "word": "udapādi,",
        "start": 449.56,
        "end": 451.3
      },
      {
        "word": "vijjā",
        "start": 451.3,
        "end": 452.04
      },
      {
        "word": "udapādi,",
        "start": 452.04,
        "end": 453.66
      },
      {
        "word": "āloko",
        "start": 457.46,
        "end": 457.46
      },
      {
        "word": "udapādi.",
        "start": 457.46,
        "end": 457.58
      }
    ]
  },
  "sn56.11_026": {
    "text": "Taṁ kho panidaṁ dukkhasamudayaṁ ariyasaccaṁ pahīnan'ti me, bhikkhave, pubbe ananussutesu dhammesu cakkhuṁ udapādi, ñāṇaṁ udapādi, paññā udapādi, vijjā udapādi, āloko udapādi.",
    "start": 457.58,
    "end": 482.06,
    "duration": 24.48,
    "words": [
      {
        "word": "Taṁ",
        "start": 457.58,
        "end": 457.58
      },
      {
        "word": "kho",
        "start": 457.58,
        "end": 457.58
      },
      {
        "word": "panidaṁ",
        "start": 457.58,
        "end": 458.38
      },
      {
        "word": "dukkhasamudayaṁ",
        "start": 458.38,
        "end": 460.14
      },
      {
        "word": "ariyasaccaṁ",
        "start": 460.14,
        "end": 462.08
      },
      {
        "word": "pahīnan'ti",
        "start": 462.08,
        "end": 463.44
      },
      {
        "word": "me,",
        "start": 463.44,
        "end": 464.08
      },
      {
        "word": "bhikkhave,",
        "start": 464.38,
        "end": 465.38
      },
      {
        "word": "pubbe",
        "start": 465.6,
        "end": 466.08
      },
      {
        "word": "ananussutesu",
        "start": 466.08,
        "end": 468.26
      },
      {
        "word": "dhammesu",
        "start": 468.26,
        "end": 469.5
      },
      {
        "word": "cakkhuṁ",
        "start": 469.5,
        "end": 470.54
      },
      {
        "word": "udapādi,",
        "start": 470.54,
        "end": 471.92
      },
      {
        "word": "ñāṇaṁ",
        "start": 471.98,
        "end": 473.02
      },
      {
        "word": "udapādi,",
        "start": 473.02,
        "end": 474.28
      },
      {
        "word": "paññā",
        "start": 474.36,
        "end": 474.94
      },
      {
        "word": "udapādi,",
        "start": 474.94,
        "end": 476.62
      },
      {
        "word": "vijjā",
        "start": 476.68,
        "end": 477.36
      },
      {
        "word": "udapādi,",
        "start": 477.36,
        "end": 478.92
      },
      {
        "word": "āloko",
        "start": 479.22,
        "end": 479.82
      },
      {
        "word": "udapādi.",
        "start": 479.82,
        "end": 482.06
      }
    ]
  },
  "sn56.11_027": {
    "text": "Idaṁ dukkhanirodhaṁ ariyasaccan'ti me, bhikkhave, pubbe ananussutesu dhammesu cakkhuṁ udapādi, ñāṇaṁ udapādi, paññā udapādi, vijjā udapādi, āloko udapādi.",
    "start": 482.06,
    "end": 504.62,
    "duration": 22.56,
    "words": [
      {
        "word": "Idaṁ",
        "start": 482.06,
        "end": 482.38
      },
      {
        "word": "dukkhanirodhaṁ",
        "start": 482.38,
        "end": 484.42
      },
      {
        "word": "ariyasaccan'ti",
        "start": 484.42,
        "end": 486.32
      },
      {
        "word": "me,",
        "start": 486.32,
        "end": 486.98
      },
      {
        "word": "bhikkhave,",
        "start": 487.26,
        "end": 488.28
      },
      {
        "word": "pubbe",
        "start": 488.76,
        "end": 489.02
      },
      {
        "word": "ananussutesu",
        "start": 489.02,
        "end": 491.14
      },
      {
        "word": "dhammesu",
        "start": 491.14,
        "end": 492.36
      },
      {
        "word": "cakkhuṁ",
        "start": 492.36,
        "end": 493.42
      },
      {
        "word": "udapādi,",
        "start": 493.42,
        "end": 494.78
      },
      {
        "word": "ñāṇaṁ",
        "start": 494.86,
        "end": 495.88
      },
      {
        "word": "udapādi,",
        "start": 495.88,
        "end": 497.16
      },
      {
        "word": "paññā",
        "start": 497.22,
        "end": 497.92
      },
      {
        "word": "udapādi,",
        "start": 497.92,
        "end": 499.5
      },
      {
        "word": "vijjā",
        "start": 499.52,
        "end": 500.2
      },
      {
        "word": "udapādi,",
        "start": 500.2,
        "end": 501.84
      },
      {
        "word": "āloko",
        "start": 502.02,
        "end": 502.84
      },
      {
        "word": "udapādi.",
        "start": 502.84,
        "end": 504.62
      }
    ]
  },
  "sn56.11_028": {
    "text": "Taṁ kho panidaṁ dukkhanirodhaṁ ariyasaccaṁ sacchikātabban'ti me, bhikkhave, pubbe ananussutesu dhammesu cakkhuṁ udapādi, ñāṇaṁ udapādi, paññā udapādi, vijjā udapādi, āloko udapādi.",
    "start": 504.76,
    "end": 531.18,
    "duration": 26.42,
    "words": [
      {
        "word": "Taṁ",
        "start": 504.76,
        "end": 505.06
      },
      {
        "word": "kho",
        "start": 505.06,
        "end": 505.34
      },
      {
        "word": "panidaṁ",
        "start": 505.34,
        "end": 506.56
      },
      {
        "word": "dukkhanirodhaṁ",
        "start": 506.56,
        "end": 508.48
      },
      {
        "word": "ariyasaccaṁ",
        "start": 508.48,
        "end": 510.26
      },
      {
        "word": "sacchikātabban'ti",
        "start": 510.26,
        "end": 512.78
      },
      {
        "word": "me,",
        "start": 512.78,
        "end": 513.46
      },
      {
        "word": "bhikkhave,",
        "start": 513.52,
        "end": 514.72
      },
      {
        "word": "pubbe",
        "start": 515.02,
        "end": 515.44
      },
      {
        "word": "ananussutesu",
        "start": 515.44,
        "end": 517.64
      },
      {
        "word": "dhammesu",
        "start": 517.64,
        "end": 518.86
      },
      {
        "word": "cakkhuṁ",
        "start": 518.86,
        "end": 520.1
      },
      {
        "word": "udapādi,",
        "start": 520.1,
        "end": 521.3
      },
      {
        "word": "ñāṇaṁ",
        "start": 521.3,
        "end": 522.4
      },
      {
        "word": "udapādi,",
        "start": 522.4,
        "end": 523.64
      },
      {
        "word": "paññā",
        "start": 523.78,
        "end": 524.46
      },
      {
        "word": "udapādi,",
        "start": 524.46,
        "end": 526.06
      },
      {
        "word": "vijjā",
        "start": 526.1,
        "end": 526.76
      },
      {
        "word": "udapādi,",
        "start": 526.76,
        "end": 528.38
      },
      {
        "word": "āloko",
        "start": 528.86,
        "end": 529.34
      },
      {
        "word": "udapādi.",
        "start": 529.34,
        "end": 531.18
      }
    ]
  },
  "sn56.11_029": {
    "text": "Taṁ kho panidaṁ dukkhanirodhaṁ ariyasaccaṁ sacchikatan'ti me, bhikkhave, pubbe ananussutesu dhammesu cakkhuṁ udapādi, ñāṇaṁ udapādi, paññā udapādi, vijjā udapādi, āloko udapādi.",
    "start": 531.28,
    "end": 557.02,
    "duration": 25.74,
    "words": [
      {
        "word": "Taṁ",
        "start": 531.28,
        "end": 531.56
      },
      {
        "word": "kho",
        "start": 531.56,
        "end": 531.9
      },
      {
        "word": "panidaṁ",
        "start": 531.9,
        "end": 533.1
      },
      {
        "word": "dukkhanirodhaṁ",
        "start": 533.1,
        "end": 535.06
      },
      {
        "word": "ariyasaccaṁ",
        "start": 535.06,
        "end": 536.8
      },
      {
        "word": "sacchikatan'ti",
        "start": 536.8,
        "end": 538.56
      },
      {
        "word": "me,",
        "start": 538.56,
        "end": 539.24
      },
      {
        "word": "bhikkhave,",
        "start": 539.52,
        "end": 540.48
      },
      {
        "word": "pubbe",
        "start": 540.76,
        "end": 541.2
      },
      {
        "word": "ananussutesu",
        "start": 541.2,
        "end": 543.36
      },
      {
        "word": "dhammesu",
        "start": 543.36,
        "end": 544.6
      },
      {
        "word": "cakkhuṁ",
        "start": 544.6,
        "end": 545.64
      },
      {
        "word": "udapādi,",
        "start": 545.64,
        "end": 547.04
      },
      {
        "word": "ñāṇaṁ",
        "start": 547.14,
        "end": 548.08
      },
      {
        "word": "udapādi,",
        "start": 548.08,
        "end": 549.3
      },
      {
        "word": "paññā",
        "start": 549.46,
        "end": 550.12
      },
      {
        "word": "udapādi,",
        "start": 550.84,
        "end": 551.74
      },
      {
        "word": "vijjā",
        "start": 552.28,
        "end": 552.44
      },
      {
        "word": "udapādi,",
        "start": 552.44,
        "end": 554.36
      },
      {
        "word": "āloko",
        "start": 554.36,
        "end": 555.04
      },
      {
        "word": "udapādi.",
        "start": 555.04,
        "end": 557.02
      }
    ]
  },
  "sn56.11_030": {
    "text": "Idaṁ dukkhanirodhagāminī paṭipadā ariyasaccan'ti me, bhikkhave, pubbe ananussutesu dhammesu cakkhuṁ udapādi, ñāṇaṁ udapādi, paññā udapādi, vijjā udapādi, āloko udapādi.",
    "start": 557.02,
    "end": 582.3,
    "duration": 25.28,
    "words": [
      {
        "word": "Idaṁ",
        "start": 557.02,
        "end": 557.5
      },
      {
        "word": "dukkhanirodhagāminī",
        "start": 557.5,
        "end": 560.44
      },
      {
        "word": "paṭipadā",
        "start": 560.44,
        "end": 561.7
      },
      {
        "word": "ariyasaccan'ti",
        "start": 561.7,
        "end": 563.78
      },
      {
        "word": "me,",
        "start": 563.78,
        "end": 564.4
      },
      {
        "word": "bhikkhave,",
        "start": 564.64,
        "end": 565.7
      },
      {
        "word": "pubbe",
        "start": 565.88,
        "end": 566.36
      },
      {
        "word": "ananussutesu",
        "start": 566.36,
        "end": 568.6
      },
      {
        "word": "dhammesu",
        "start": 568.6,
        "end": 569.86
      },
      {
        "word": "cakkhuṁ",
        "start": 569.86,
        "end": 571.28
      },
      {
        "word": "udapādi,",
        "start": 571.28,
        "end": 572.36
      },
      {
        "word": "ñāṇaṁ",
        "start": 573.7,
        "end": 573.7
      },
      {
        "word": "udapādi,",
        "start": 573.7,
        "end": 574.68
      },
      {
        "word": "paññā",
        "start": 574.82,
        "end": 575.3
      },
      {
        "word": "udapādi,",
        "start": 575.3,
        "end": 577.16
      },
      {
        "word": "vijjā",
        "start": 577.16,
        "end": 577.76
      },
      {
        "word": "udapādi,",
        "start": 577.76,
        "end": 579.48
      },
      {
        "word": "āloko",
        "start": 579.68,
        "end": 580.36
      },
      {
        "word": "udapādi.",
        "start": 580.36,
        "end": 582.3
      }
    ]
  },
  "sn56.11_031": {
    "text": "Taṁ kho panidaṁ dukkhanirodhagāminī paṭipadā ariyasaccaṁ bhāvetabban'ti me, bhikkhave, pubbe ananussutesu dhammesu cakkhuṁ udapādi, ñāṇaṁ udapādi, paññā udapādi, vijjā udapādi, āloko udapādi.",
    "start": 582.34,
    "end": 610.8,
    "duration": 28.46,
    "words": [
      {
        "word": "Taṁ",
        "start": 582.34,
        "end": 582.6
      },
      {
        "word": "kho",
        "start": 582.6,
        "end": 582.88
      },
      {
        "word": "panidaṁ",
        "start": 582.88,
        "end": 584.12
      },
      {
        "word": "dukkhanirodhagāminī",
        "start": 584.12,
        "end": 586.98
      },
      {
        "word": "paṭipadā",
        "start": 586.98,
        "end": 588.28
      },
      {
        "word": "ariyasaccaṁ",
        "start": 588.28,
        "end": 590.3
      },
      {
        "word": "bhāvetabban'ti",
        "start": 590.3,
        "end": 592.42
      },
      {
        "word": "me,",
        "start": 592.42,
        "end": 593.14
      },
      {
        "word": "bhikkhave,",
        "start": 593.18,
        "end": 594.78
      },
      {
        "word": "pubbe",
        "start": 594.84,
        "end": 595.08
      },
      {
        "word": "ananussutesu",
        "start": 595.08,
        "end": 597.22
      },
      {
        "word": "dhammesu",
        "start": 597.22,
        "end": 598.48
      },
      {
        "word": "cakkhuṁ",
        "start": 598.48,
        "end": 599.5
      },
      {
        "word": "udapādi,",
        "start": 599.5,
        "end": 600.82
      },
      {
        "word": "ñāṇaṁ",
        "start": 600.98,
        "end": 601.86
      },
      {
        "word": "udapādi,",
        "start": 601.86,
        "end": 603.28
      },
      {
        "word": "paññā",
        "start": 603.4,
        "end": 604.02
      },
      {
        "word": "udapādi,",
        "start": 604.02,
        "end": 605.6
      },
      {
        "word": "vijjā",
        "start": 605.66,
        "end": 606.36
      },
      {
        "word": "udapādi,",
        "start": 606.36,
        "end": 607.9
      },
      {
        "word": "āloko",
        "start": 608.08,
        "end": 608.86
      },
      {
        "word": "udapādi.",
        "start": 608.86,
        "end": 610.8
      }
    ]
  },
  "sn56.11_032": {
    "text": "Taṁ kho panidaṁ dukkhanirodhagāminī paṭipadā ariyasaccaṁ bhāvitan'ti me, bhikkhave, pubbe ananussutesu dhammesu cakkhuṁ udapādi, ñāṇaṁ udapādi, paññā udapādi, vijjā udapādi, āloko udapādi.",
    "start": 610.84,
    "end": 639.5,
    "duration": 28.66,
    "words": [
      {
        "word": "Taṁ",
        "start": 610.84,
        "end": 611.08
      },
      {
        "word": "kho",
        "start": 611.08,
        "end": 611.38
      },
      {
        "word": "panidaṁ",
        "start": 611.38,
        "end": 612.6
      },
      {
        "word": "dukkhanirodhagāminī",
        "start": 612.6,
        "end": 615.54
      },
      {
        "word": "paṭipadā",
        "start": 615.54,
        "end": 616.84
      },
      {
        "word": "ariyasaccaṁ",
        "start": 616.84,
        "end": 618.88
      },
      {
        "word": "bhāvitan'ti",
        "start": 618.88,
        "end": 620.18
      },
      {
        "word": "me,",
        "start": 620.18,
        "end": 620.8
      },
      {
        "word": "bhikkhave,",
        "start": 620.86,
        "end": 622.04
      },
      {
        "word": "pubbe",
        "start": 622.28,
        "end": 622.76
      },
      {
        "word": "ananussutesu",
        "start": 622.76,
        "end": 624.94
      },
      {
        "word": "dhammesu",
        "start": 624.94,
        "end": 626.18
      },
      {
        "word": "cakkhuṁ",
        "start": 626.18,
        "end": 627.24
      },
      {
        "word": "udapādi,",
        "start": 627.24,
        "end": 628.6
      },
      {
        "word": "ñāṇaṁ",
        "start": 628.68,
        "end": 629.68
      },
      {
        "word": "udapādi,",
        "start": 629.68,
        "end": 630.98
      },
      {
        "word": "paññā",
        "start": 631.12,
        "end": 631.76
      },
      {
        "word": "udapādi,",
        "start": 631.76,
        "end": 633.36
      },
      {
        "word": "vijjā",
        "start": 633.4,
        "end": 634.02
      },
      {
        "word": "udapādi,",
        "start": 634.02,
        "end": 635.68
      },
      {
        "word": "āloko",
        "start": 635.86,
        "end": 636.62
      },
      {
        "word": "udapādi.",
        "start": 637.0,
        "end": 639.5
      }
    ]
  },
  "sn56.11_033": {
    "text": "Yāvakīvañca me, bhikkhave, imesu catūsu ariyasaccesu evaṁ tiparivaṭṭaṁ dvādasākāraṁ yathābhūtaṁ ñāṇadassanaṁ na suvisuddhaṁ ahosi, neva tāvāhaṁ, bhikkhave, sadevake loke samārake sabrahmake sassamaṇabrāhmaṇiyā pajāya sadevamanussāya anuttaraṁ sammāsambodhiṁ abhisambuddho'ti paccaññāsiṁ.",
    "start": 640.14,
    "end": 683.14,
    "duration": 43.0,
    "words": [
      {
        "word": "Yāvakīvañca",
        "start": 640.14,
        "end": 641.62
      },
      {
        "word": "me,",
        "start": 641.62,
        "end": 642.38
      },
      {
        "word": "bhikkhave,",
        "start": 642.68,
        "end": 643.96
      },
      {
        "word": "imesu",
        "start": 644.08,
        "end": 644.64
      },
      {
        "word": "catūsu",
        "start": 644.64,
        "end": 645.54
      },
      {
        "word": "ariyasaccesu",
        "start": 645.54,
        "end": 647.66
      },
      {
        "word": "evaṁ",
        "start": 647.66,
        "end": 648.64
      },
      {
        "word": "tiparivaṭṭaṁ",
        "start": 648.64,
        "end": 650.5
      },
      {
        "word": "dvādasākāraṁ",
        "start": 650.5,
        "end": 653.0
      },
      {
        "word": "yathābhūtaṁ",
        "start": 653.0,
        "end": 654.72
      },
      {
        "word": "ñāṇadassanaṁ",
        "start": 654.72,
        "end": 656.84
      },
      {
        "word": "na",
        "start": 656.84,
        "end": 657.0
      },
      {
        "word": "suvisuddhaṁ",
        "start": 657.0,
        "end": 658.54
      },
      {
        "word": "ahosi,",
        "start": 658.54,
        "end": 659.62
      },
      {
        "word": "neva",
        "start": 659.66,
        "end": 660.16
      },
      {
        "word": "tāvāhaṁ,",
        "start": 660.16,
        "end": 661.9
      },
      {
        "word": "bhikkhave,",
        "start": 662.26,
        "end": 663.14
      },
      {
        "word": "sadevake",
        "start": 663.28,
        "end": 664.26
      },
      {
        "word": "loke",
        "start": 664.26,
        "end": 665.26
      },
      {
        "word": "samārake",
        "start": 665.26,
        "end": 666.84
      },
      {
        "word": "sabrahmake",
        "start": 666.84,
        "end": 668.34
      },
      {
        "word": "sassamaṇabrāhmaṇiyā",
        "start": 668.34,
        "end": 671.32
      },
      {
        "word": "pajāya",
        "start": 671.32,
        "end": 672.38
      },
      {
        "word": "sadevamanussāya",
        "start": 672.38,
        "end": 674.88
      },
      {
        "word": "anuttaraṁ",
        "start": 674.88,
        "end": 676.44
      },
      {
        "word": "sammāsambodhiṁ",
        "start": 676.44,
        "end": 679.06
      },
      {
        "word": "abhisambuddho'ti",
        "start": 679.06,
        "end": 681.38
      },
      {
        "word": "paccaññāsiṁ.",
        "start": 681.38,
        "end": 683.14
      }
    ]
  },
  "sn56.11_034": {
    "text": "Yato ca kho me, bhikkhave, imesu catūsu ariyasaccesu evaṁ tiparivaṭṭaṁ dvādasākāraṁ yathābhūtaṁ ñāṇadassanaṁ suvisuddhaṁ ahosi, athāhaṁ, bhikkhave, sadevake loke samārake sabrahmake sassamaṇabrāhmaṇiyā pajāya sadevamanussāya anuttaraṁ sammāsambodhiṁ abhisambuddho'ti paccaññāsiṁ.",
    "start": 683.34,
    "end": 724.44,
    "duration": 41.1,
    "words": [
      {
        "word": "Yato",
        "start": 683.34,
        "end": 683.44
      },
      {
        "word": "ca",
        "start": 683.44,
        "end": 683.9
      },
      {
        "word": "kho",
        "start": 683.9,
        "end": 684.38
      },
      {
        "word": "me,",
        "start": 684.38,
        "end": 685.1
      },
      {
        "word": "bhikkhave,",
        "start": 685.18,
        "end": 686.66
      },
      {
        "word": "imesu",
        "start": 686.66,
        "end": 687.28
      },
      {
        "word": "catūsu",
        "start": 687.28,
        "end": 688.16
      },
      {
        "word": "ariyasaccesu",
        "start": 688.16,
        "end": 690.3
      },
      {
        "word": "evaṁ",
        "start": 690.3,
        "end": 691.22
      },
      {
        "word": "tiparivaṭṭaṁ",
        "start": 691.22,
        "end": 693.34
      },
      {
        "word": "dvādasākāraṁ",
        "start": 693.34,
        "end": 695.58
      },
      {
        "word": "yathābhūtaṁ",
        "start": 695.58,
        "end": 697.28
      },
      {
        "word": "ñāṇadassanaṁ",
        "start": 697.28,
        "end": 699.26
      },
      {
        "word": "suvisuddhaṁ",
        "start": 699.26,
        "end": 700.84
      },
      {
        "word": "ahosi,",
        "start": 700.84,
        "end": 701.88
      },
      {
        "word": "athāhaṁ,",
        "start": 702.08,
        "end": 703.16
      },
      {
        "word": "bhikkhave,",
        "start": 703.4,
        "end": 704.42
      },
      {
        "word": "sadevake",
        "start": 704.5,
        "end": 705.48
      },
      {
        "word": "loke",
        "start": 705.48,
        "end": 706.52
      },
      {
        "word": "samārake",
        "start": 706.52,
        "end": 708.06
      },
      {
        "word": "sabrahmake",
        "start": 708.06,
        "end": 709.62
      },
      {
        "word": "sassamaṇabrāhmaṇiyā",
        "start": 709.62,
        "end": 712.58
      },
      {
        "word": "pajāya",
        "start": 712.58,
        "end": 713.62
      },
      {
        "word": "sadevamanussāya",
        "start": 713.62,
        "end": 716.16
      },
      {
        "word": "anuttaraṁ",
        "start": 716.16,
        "end": 717.7
      },
      {
        "word": "sammāsambodhiṁ",
        "start": 717.7,
        "end": 720.3
      },
      {
        "word": "abhisambuddho'ti",
        "start": 720.3,
        "end": 722.52
      },
      {
        "word": "paccaññāsiṁ.",
        "start": 722.52,
        "end": 724.44
      }
    ]
  },
  "sn56.11_035": {
    "text": "Ñāṇañca pana me dassanaṁ udapādi:",
    "start": 724.96,
    "end": 728.98,
    "duration": 4.02,
    "words": [
      {
        "word": "Ñāṇañca",
        "start": 724.96,
        "end": 725.38
      },
      {
        "word": "pana",
        "start": 725.38,
        "end": 725.8
      },
      {
        "word": "me",
        "start": 725.8,
        "end": 726.22
      },
      {
        "word": "dassanaṁ",
        "start": 726.22,
        "end": 727.72
      },
      {
        "word": "udapādi:",
        "start": 727.72,
        "end": 728.98
      }
    ]
  },
  "sn56.11_036": {
    "text": "akuppā me vimutti, ayamantimā jāti, natthi dāni punabbhavo'ti.",
    "start": 729.32,
    "end": 737.23,
    "duration": 7.91,
    "words": [
      {
        "word": "akuppā",
        "start": 729.32,
        "end": 729.92
      },
      {
        "word": "me",
        "start": 729.92,
        "end": 730.26
      },
      {
        "word": "vimutti,",
        "start": 730.26,
        "end": 731.76
      },
      {
        "word": "ayamantimā",
        "start": 731.8,
        "end": 733.16
      },
      {
        "word": "jāti,",
        "start": 733.16,
        "end": 734.1
      },
      {
        "word": "natthi",
        "start": 734.32,
        "end": 734.78
      },
      {
        "word": "dāni",
        "start": 734.78,
        "end": 735.48
      },
      {
        "word": "punabbhavo'ti.",
        "start": 735.48,
        "end": 737.23
      }
    ]
  },
  "sn56.11_037": {
    "text": "Idamavoca bhagavā.",
    "start": 737.66,
    "end": 739.9,
    "duration": 2.24,
    "words": [
      {
        "word": "Idamavoca",
        "start": 737.66,
        "end": 738.62
      },
      {
        "word": "bhagavā.",
        "start": 738.62,
        "end": 739.9
      }
    ]
  },
  "sn56.11_038": {
    "text": "Attamanā pañcavaggiyā bhikkhū bhagavato bhāsitaṁ abhinandunti.",
    "start": 740.28,
    "end": 748.66,
    "duration": 8.38,
    "words": [
      {
        "word": "Attamanā",
        "start": 740.28,
        "end": 741.1
      },
      {
        "word": "pañcavaggiyā",
        "start": 741.1,
        "end": 743.1
      },
      {
        "word": "bhikkhū",
        "start": 743.1,
        "end": 744.22
      },
      {
        "word": "bhagavato",
        "start": 744.22,
        "end": 745.2
      },
      {
        "word": "bhāsitaṁ",
        "start": 745.2,
        "end": 746.86
      },
      {
        "word": "abhinandunti.",
        "start": 746.86,
        "end": 748.66
      }
    ]
  },
  "sn56.11_039": {
    "text": "Imasmiñca pana veyyākaraṇasmiṁ bhaññamāne āyasmato koṇḍaññassa virajaṁ vītamalaṁ dhammacakkhuṁ udapādi:",
    "start": 748.66,
    "end": 763.4,
    "duration": 14.74,
    "words": [
      {
        "word": "Imasmiñca",
        "start": 748.66,
        "end": 749.64
      },
      {
        "word": "pana",
        "start": 749.64,
        "end": 750.0
      },
      {
        "word": "veyyākaraṇasmiṁ",
        "start": 750.0,
        "end": 752.72
      },
      {
        "word": "bhaññamāne",
        "start": 752.72,
        "end": 754.04
      },
      {
        "word": "āyasmato",
        "start": 754.04,
        "end": 755.68
      },
      {
        "word": "koṇḍaññassa",
        "start": 755.68,
        "end": 757.66
      },
      {
        "word": "virajaṁ",
        "start": 757.66,
        "end": 758.92
      },
      {
        "word": "vītamalaṁ",
        "start": 758.92,
        "end": 760.18
      },
      {
        "word": "dhammacakkhuṁ",
        "start": 760.3,
        "end": 762.04
      },
      {
        "word": "udapādi:",
        "start": 762.04,
        "end": 763.4
      }
    ]
  },
  "sn56.11_040": {
    "text": "yaṁ kiñci samudayadhammaṁ sabbaṁ taṁ nirodhadhamman'ti.",
    "start": 763.48,
    "end": 771.4,
    "duration": 7.92,
    "words": [
      {
        "word": "yaṁ",
        "start": 763.48,
        "end": 763.72
      },
      {
        "word": "kiñci",
        "start": 763.72,
        "end": 764.32
      },
      {
        "word": "samudayadhammaṁ",
        "start": 764.32,
        "end": 766.52
      },
      {
        "word": "sabbaṁ",
        "start": 766.52,
        "end": 767.46
      },
      {
        "word": "taṁ",
        "start": 768.14,
        "end": 768.64
      },
      {
        "word": "nirodhadhamman'ti.",
        "start": 768.64,
        "end": 771.4
      }
    ]
  },
  "sn56.11_041": {
    "text": "Pavattite ca pana bhagavatā dhammacakke bhummā devā saddamanussāvesuṁ:",
    "start": 771.54,
    "end": 781.52,
    "duration": 9.98,
    "words": [
      {
        "word": "Pavattite",
        "start": 771.54,
        "end": 772.42
      },
      {
        "word": "ca",
        "start": 772.44,
        "end": 773.06
      },
      {
        "word": "pana",
        "start": 773.06,
        "end": 773.28
      },
      {
        "word": "bhagavatā",
        "start": 773.28,
        "end": 774.28
      },
      {
        "word": "dhammacakke",
        "start": 774.28,
        "end": 776.1
      },
      {
        "word": "bhummā",
        "start": 776.1,
        "end": 777.2
      },
      {
        "word": "devā",
        "start": 778.08,
        "end": 778.9
      },
      {
        "word": "saddamanussāvesuṁ:",
        "start": 778.9,
        "end": 781.52
      }
    ]
  },
  "sn56.11_042": {
    "text": "etaṁ bhagavatā bārāṇasiyaṁ isipatane migadāye anuttaraṁ dhammacakkaṁ pavattitaṁ appaṭivattiyaṁ samaṇena vā brāhmaṇena vā devena vā mārena vā brahmunā vā kenaci vā lokasmin'ti.",
    "start": 782.0,
    "end": 808.26,
    "duration": 26.26,
    "words": [
      {
        "word": "etaṁ",
        "start": 782.0,
        "end": 782.36
      },
      {
        "word": "bhagavatā",
        "start": 782.36,
        "end": 783.46
      },
      {
        "word": "bārāṇasiyaṁ",
        "start": 783.46,
        "end": 785.76
      },
      {
        "word": "isipatane",
        "start": 785.76,
        "end": 786.66
      },
      {
        "word": "migadāye",
        "start": 786.66,
        "end": 788.36
      },
      {
        "word": "anuttaraṁ",
        "start": 788.36,
        "end": 790.16
      },
      {
        "word": "dhammacakkaṁ",
        "start": 790.16,
        "end": 791.9
      },
      {
        "word": "pavattitaṁ",
        "start": 791.9,
        "end": 793.36
      },
      {
        "word": "appaṭivattiyaṁ",
        "start": 793.36,
        "end": 795.48
      },
      {
        "word": "samaṇena",
        "start": 795.48,
        "end": 796.64
      },
      {
        "word": "vā",
        "start": 796.64,
        "end": 797.1
      },
      {
        "word": "brāhmaṇena",
        "start": 797.1,
        "end": 798.78
      },
      {
        "word": "vā",
        "start": 798.78,
        "end": 799.22
      },
      {
        "word": "devena",
        "start": 799.22,
        "end": 800.58
      },
      {
        "word": "vā",
        "start": 800.58,
        "end": 801.06
      },
      {
        "word": "mārena",
        "start": 801.06,
        "end": 802.46
      },
      {
        "word": "vā",
        "start": 802.46,
        "end": 802.92
      },
      {
        "word": "brahmunā",
        "start": 802.92,
        "end": 804.22
      },
      {
        "word": "vā",
        "start": 804.22,
        "end": 804.68
      },
      {
        "word": "kenaci",
        "start": 804.68,
        "end": 805.68
      },
      {
        "word": "vā",
        "start": 805.7,
        "end": 806.24
      },
      {
        "word": "lokasmin'ti.",
        "start": 806.24,
        "end": 808.26
      }
    ]
  },
  "sn56.11_043": {
    "text": "Bhummānaṁ devānaṁ saddaṁ sutvā cātumahārājikā devā saddamanussāvesuṁ:",
    "start": 808.32,
    "end": 820.44,
    "duration": 12.12,
    "words": [
      {
        "word": "Bhummānaṁ",
        "start": 808.32,
        "end": 809.64
      },
      {
        "word": "devānaṁ",
        "start": 809.64,
        "end": 811.14
      },
      {
        "word": "saddaṁ",
        "start": 811.14,
        "end": 812.16
      },
      {
        "word": "sutvā",
        "start": 812.16,
        "end": 812.94
      },
      {
        "word": "cātumahārājikā",
        "start": 813.3,
        "end": 816.08
      },
      {
        "word": "devā",
        "start": 816.08,
        "end": 816.98
      },
      {
        "word": "saddamanussāvesuṁ:",
        "start": 817.9,
        "end": 820.44
      }
    ]
  },
  "sn56.11_044": {
    "text": "etaṁ bhagavatā bārāṇasiyaṁ isipatane migadāye anuttaraṁ dhammacakkaṁ pavattitaṁ, appaṭivattiyaṁ samaṇena vā brāhmaṇena vā devena vā mārena vā brahmunā vā kenaci vā lokasmin'ti.",
    "start": 820.64,
    "end": 917.72,
    "duration": 97.08,
    "words": [
      {
        "word": "etaṁ",
        "start": 820.64,
        "end": 821.16
      },
      {
        "word": "bhagavatā",
        "start": 821.16,
        "end": 822.24
      },
      {
        "word": "bārāṇasiyaṁ",
        "start": 822.24,
        "end": 823.54
      },
      {
        "word": "isipatane",
        "start": 823.54,
        "end": 824.06
      },
      {
        "word": "migadāye",
        "start": 824.06,
        "end": 824.06
      },
      {
        "word": "anuttaraṁ",
        "start": 824.06,
        "end": 824.06
      },
      {
        "word": "dhammacakkaṁ",
        "start": 824.06,
        "end": 824.56
      },
      {
        "word": "pavattitaṁ,",
        "start": 900.86,
        "end": 903.1
      },
      {
        "word": "appaṭivattiyaṁ",
        "start": 903.44,
        "end": 904.92
      },
      {
        "word": "samaṇena",
        "start": 904.92,
        "end": 906.1
      },
      {
        "word": "vā",
        "start": 906.1,
        "end": 906.58
      },
      {
        "word": "brāhmaṇena",
        "start": 906.58,
        "end": 908.26
      },
      {
        "word": "vā",
        "start": 908.26,
        "end": 908.76
      },
      {
        "word": "devena",
        "start": 908.76,
        "end": 910.12
      },
      {
        "word": "vā",
        "start": 910.12,
        "end": 910.7
      },
      {
        "word": "mārena",
        "start": 910.7,
        "end": 911.98
      },
      {
        "word": "vā",
        "start": 911.98,
        "end": 912.38
      },
      {
        "word": "brahmunā",
        "start": 912.38,
        "end": 913.72
      },
      {
        "word": "vā",
        "start": 913.72,
        "end": 914.22
      },
      {
        "word": "kenaci",
        "start": 914.22,
        "end": 915.16
      },
      {
        "word": "vā",
        "start": 915.16,
        "end": 915.68
      },
      {
        "word": "lokasmin'ti.",
        "start": 915.68,
        "end": 917.72
      }
    ]
  },
  "sn56.11_045": {
    "text": "Cātumahārājikānaṁ devānaṁ saddaṁ sutvā tāvatiṁsā devā saddamanussāvesuṁ.",
    "start": 917.88,
    "end": 951.48,
    "duration": 33.6,
    "words": [
      {
        "word": "Cātumahārājikānaṁ",
        "start": 917.88,
        "end": 919.1
      },
      {
        "word": "devānaṁ",
        "start": 945.62,
        "end": 947.12
      },
      {
        "word": "saddaṁ",
        "start": 947.12,
        "end": 948.4
      },
      {
        "word": "sutvā",
        "start": 948.4,
        "end": 948.82
      },
      {
        "word": "tāvatiṁsā",
        "start": 948.82,
        "end": 951.42
      },
      {
        "word": "devā",
        "start": 951.42,
        "end": 951.42
      },
      {
        "word": "saddamanussāvesuṁ.",
        "start": 951.42,
        "end": 951.48
      }
    ]
  },
  "sn56.11_046": {
    "text": "Tāvatiṁsānaṁ devānaṁ saddaṁ sutvā yāmā devā saddamanussāvesuṁ.",
    "start": 951.68,
    "end": 973.5,
    "duration": 21.82,
    "words": [
      {
        "word": "Tāvatiṁsānaṁ",
        "start": 951.68,
        "end": 952.58
      },
      {
        "word": "devānaṁ",
        "start": 952.58,
        "end": 952.96
      },
      {
        "word": "saddaṁ",
        "start": 952.96,
        "end": 952.96
      },
      {
        "word": "sutvā",
        "start": 952.96,
        "end": 953.18
      },
      {
        "word": "yāmā",
        "start": 953.18,
        "end": 954.86
      },
      {
        "word": "devā",
        "start": 954.86,
        "end": 956.54
      },
      {
        "word": "saddamanussāvesuṁ.",
        "start": 971.7,
        "end": 973.5
      }
    ]
  },
  "sn56.11_047": {
    "text": "Yāmānaṁ devānaṁ saddaṁ sutvā tusitā devā saddamanussāvesuṁ.",
    "start": 974.18,
    "end": 980.31,
    "duration": 6.13,
    "words": [
      {
        "word": "Yāmānaṁ",
        "start": 974.18,
        "end": 975.36
      },
      {
        "word": "devānaṁ",
        "start": 975.36,
        "end": 976.6
      },
      {
        "word": "saddaṁ",
        "start": 976.6,
        "end": 976.8
      },
      {
        "word": "sutvā",
        "start": 976.8,
        "end": 976.98
      },
      {
        "word": "tusitā",
        "start": 976.98,
        "end": 977.3
      },
      {
        "word": "devā",
        "start": 977.3,
        "end": 977.86
      },
      {
        "word": "saddamanussāvesuṁ.",
        "start": 980.31,
        "end": 980.31
      }
    ]
  },
  "sn56.11_048": {
    "text": "Tusitānaṁ devānaṁ saddaṁ sutvā nimmānaratī devā saddamanussāvesuṁ.",
    "start": 980.31,
    "end": 980.31,
    "duration": 0.0,
    "words": [
      {
        "word": "Tusitānaṁ",
        "start": 980.31,
        "end": 980.31
      },
      {
        "word": "devānaṁ",
        "start": 980.31,
        "end": 980.31
      },
      {
        "word": "saddaṁ",
        "start": 980.31,
        "end": 980.31
      },
      {
        "word": "sutvā",
        "start": 980.31,
        "end": 980.31
      },
      {
        "word": "nimmānaratī",
        "start": 980.31,
        "end": 980.31
      },
      {
        "word": "devā",
        "start": 980.31,
        "end": 980.31
      },
      {
        "word": "saddamanussāvesuṁ.",
        "start": 980.31,
        "end": 980.31
      }
    ]
  },
  "sn56.11_049": {
    "text": "Nimmānaratīnaṁ devānaṁ saddaṁ sutvā paranimmitavasavattī devā saddamanussāvesuṁ.",
    "start": 980.31,
    "end": 980.31,
    "duration": 0.0,
    "words": [
      {
        "word": "Nimmānaratīnaṁ",
        "start": 980.31,
        "end": 980.31
      },
      {
        "word": "devānaṁ",
        "start": 980.31,
        "end": 980.31
      },
      {
        "word": "saddaṁ",
        "start": 980.31,
        "end": 980.31
      },
      {
        "word": "sutvā",
        "start": 980.31,
        "end": 980.31
      },
      {
        "word": "paranimmitavasavattī",
        "start": 980.31,
        "end": 980.31
      },
      {
        "word": "devā",
        "start": 980.31,
        "end": 980.31
      },
      {
        "word": "saddamanussāvesuṁ.",
        "start": 980.31,
        "end": 980.31
      }
    ]
  },
  "sn56.11_050": {
    "text": "Paranimmitavasavattīnaṁ devānaṁ saddaṁ sutvā brahmakāyikā devā saddamanussāvesuṁ:",
    "start": 980.31,
    "end": 980.31,
    "duration": 0.0,
    "words": [
      {
        "word": "Paranimmitavasavattīnaṁ",
        "start": 980.31,
        "end": 980.31
      },
      {
        "word": "devānaṁ",
        "start": 980.31,
        "end": 980.31
      },
      {
        "word": "saddaṁ",
        "start": 980.31,
        "end": 980.31
      },
      {
        "word": "sutvā",
        "start": 980.31,
        "end": 980.31
      },
      {
        "word": "brahmakāyikā",
        "start": 980.31,
        "end": 980.31
      },
      {
        "word": "devā",
        "start": 980.31,
        "end": 980.31
      },
      {
        "word": "saddamanussāvesuṁ:",
        "start": 980.31,
        "end": 980.31
      }
    ]
  },
  "sn56.11_051": {
    "text": "etaṁ bhagavatā bārāṇasiyaṁ isipatane migadāye anuttaraṁ dhammacakkaṁ pavattitaṁ appaṭivattiyaṁ samaṇena vā brāhmaṇena vā devena vā mārena vā brahmunā vā kenaci vā lokasmin'ti.",
    "start": 980.31,
    "end": 980.31,
    "duration": 0.0,
    "words": [
      {
        "word": "etaṁ",
        "start": 980.31,
        "end": 980.31
      },
      {
        "word": "bhagavatā",
        "start": 980.31,
        "end": 980.31
      },
      {
        "word": "bārāṇasiyaṁ",
        "start": 980.31,
        "end": 980.31
      },
      {
        "word": "isipatane",
        "start": 980.31,
        "end": 980.31
      },
      {
        "word": "migadāye",
        "start": 980.31,
        "end": 980.31
      },
      {
        "word": "anuttaraṁ",
        "start": 980.31,
        "end": 980.31
      },
      {
        "word": "dhammacakkaṁ",
        "start": 980.31,
        "end": 980.31
      },
      {
        "word": "pavattitaṁ",
        "start": 980.31,
        "end": 980.31
      },
      {
        "word": "appaṭivattiyaṁ",
        "start": 980.31,
        "end": 980.31
      },
      {
        "word": "samaṇena",
        "start": 980.31,
        "end": 980.31
      },
      {
        "word": "vā",
        "start": 980.31,
        "end": 980.31
      },
      {
        "word": "brāhmaṇena",
        "start": 980.31,
        "end": 980.31
      },
      {
        "word": "vā",
        "start": 980.31,
        "end": 980.31
      },
      {
        "word": "devena",
        "start": 980.31,
        "end": 980.31
      },
      {
        "word": "vā",
        "start": 980.31,
        "end": 980.31
      },
      {
        "word": "mārena",
        "start": 980.31,
        "end": 980.31
      },
      {
        "word": "vā",
        "start": 980.31,
        "end": 980.31
      },
      {
        "word": "brahmunā",
        "start": 980.31,
        "end": 980.31
      },
      {
        "word": "vā",
        "start": 980.31,
        "end": 980.31
      },
      {
        "word": "kenaci",
        "start": 980.31,
        "end": 980.31
      },
      {
        "word": "vā",
        "start": 980.31,
        "end": 980.31
      },
      {
        "word": "lokasmin'ti.",
        "start": 980.31,
        "end": 980.31
      }
    ]
  },
  "sn56.11_052": {
    "text": "Itiha tena khaṇena tena layena tena muhuttena yāva brahmalokā saddo abbhuggacchi.",
    "start": 980.31,
    "end": 980.31,
    "duration": 0.0,
    "words": [
      {
        "word": "Itiha",
        "start": 980.31,
        "end": 980.31
      },
      {
        "word": "tena",
        "start": 980.31,
        "end": 980.31
      },
      {
        "word": "khaṇena",
        "start": 980.31,
        "end": 980.31
      },
      {
        "word": "tena",
        "start": 980.31,
        "end": 980.31
      },
      {
        "word": "layena",
        "start": 980.31,
        "end": 980.31
      },
      {
        "word": "tena",
        "start": 980.31,
        "end": 980.31
      },
      {
        "word": "muhuttena",
        "start": 980.31,
        "end": 980.31
      },
      {
        "word": "yāva",
        "start": 980.31,
        "end": 980.31
      },
      {
        "word": "brahmalokā",
        "start": 980.31,
        "end": 980.31
      },
      {
        "word": "saddo",
        "start": 980.31,
        "end": 980.31
      },
      {
        "word": "abbhuggacchi.",
        "start": 980.31,
        "end": 980.31
      }
    ]
  },
  "sn56.11_053": {
    "text": "Ayañca dasasahassilokadhātu saṅkampi sampakampi sampavedhi, appamāṇo ca uḷāro obhāso loke pāturahosi atikkamma devānaṁ devānubhāvanti.",
    "start": 980.31,
    "end": 980.31,
    "duration": 0.0,
    "words": [
      {
        "word": "Ayañca",
        "start": 980.31,
        "end": 980.31
      },
      {
        "word": "dasasahassilokadhātu",
        "start": 980.31,
        "end": 980.31
      },
      {
        "word": "saṅkampi",
        "start": 980.31,
        "end": 980.31
      },
      {
        "word": "sampakampi",
        "start": 980.31,
        "end": 980.31
      },
      {
        "word": "sampavedhi,",
        "start": 980.31,
        "end": 980.31
      },
      {
        "word": "appamāṇo",
        "start": 980.31,
        "end": 980.31
      },
      {
        "word": "ca",
        "start": 980.31,
        "end": 980.31
      },
      {
        "word": "uḷāro",
        "start": 980.31,
        "end": 980.31
      },
      {
        "word": "obhāso",
        "start": 980.31,
        "end": 980.31
      },
      {
        "word": "loke",
        "start": 980.31,
        "end": 980.31
      },
      {
        "word": "pāturahosi",
        "start": 980.31,
        "end": 980.31
      },
      {
        "word": "atikkamma",
        "start": 980.31,
        "end": 980.31
      },
      {
        "word": "devānaṁ",
        "start": 980.31,
        "end": 980.31
      },
      {
        "word": "devānubhāvanti.",
        "start": 980.31,
        "end": 980.31
      }
    ]
  },
  "sn56.11_054": {
    "text": "Atha kho bhagavā imaṁ udānaṁ udānesi:",
    "start": 980.31,
    "end": 980.31,
    "duration": 0.0,
    "words": [
      {
        "word": "Atha",
        "start": 980.31,
        "end": 980.31
      },
      {
        "word": "kho",
        "start": 980.31,
        "end": 980.31
      },
      {
        "word": "bhagavā",
        "start": 980.31,
        "end": 980.31
      },
      {
        "word": "imaṁ",
        "start": 980.31,
        "end": 980.31
      },
      {
        "word": "udānaṁ",
        "start": 980.31,
        "end": 980.31
      },
      {
        "word": "udānesi:",
        "start": 980.31,
        "end": 980.31
      }
    ]
  },
  "sn56.11_055": {
    "text": "aññāsi vata bho, koṇḍañño, aññāsi vata bho, koṇḍañño'ti.",
    "start": 980.31,
    "end": 980.31,
    "duration": 0.0,
    "words": [
      {
        "word": "aññāsi",
        "start": 980.31,
        "end": 980.31
      },
      {
        "word": "vata",
        "start": 980.31,
        "end": 980.31
      },
      {
        "word": "bho,",
        "start": 980.31,
        "end": 980.31
      },
      {
        "word": "koṇḍañño,",
        "start": 980.31,
        "end": 980.31
      },
      {
        "word": "aññāsi",
        "start": 980.31,
        "end": 980.31
      },
      {
        "word": "vata",
        "start": 980.31,
        "end": 980.31
      },
      {
        "word": "bho,",
        "start": 980.31,
        "end": 980.31
      },
      {
        "word": "koṇḍañño'ti.",
        "start": 980.31,
        "end": 980.31
      }
    ]
  },
  "sn56.11_056": {
    "text": "Iti hidaṁ āyasmato koṇḍaññassa aññāsikoṇḍañño tveva nāmaṁ ahosīti.",
    "start": 980.31,
    "end": 980.31,
    "duration": 0.0,
    "words": [
      {
        "word": "Iti",
        "start": 980.31,
        "end": 980.31
      },
      {
        "word": "hidaṁ",
        "start": 980.31,
        "end": 980.31
      },
      {
        "word": "āyasmato",
        "start": 980.31,
        "end": 980.31
      },
      {
        "word": "koṇḍaññassa",
        "start": 980.31,
        "end": 980.31
      },
      {
        "word": "aññāsikoṇḍañño",
        "start": 980.31,
        "end": 980.31
      },
      {
        "word": "tveva",
        "start": 980.31,
        "end": 980.31
      },
      {
        "word": "nāmaṁ",
        "start": 980.31,
        "end": 980.31
      },
      {
        "word": "ahosīti.",
        "start": 980.31,
        "end": 980.31
      }
    ]
  }
}